youtube_clipper/__init__.py
youtube_clipper/cli.py
youtube_clipper/converters/__init__.py
youtube_clipper/converters/exc.py
youtube_clipper/converters/model.py
youtube_clipper/converters/registry.py
youtube_clipper/converters/ttml_to_srt.py
youtube_clipper/downloader.py
youtube_clipper/parsers/__init__.py
youtube_clipper/parsers/model.py
youtube_clipper/parsers/registry.py
youtube_clipper/parsers/srt.py
youtube_clipper/parsers/vtt.py
youtube_clipper/searcher.py
youtube_clipper/utils.py
youtube_clipper-1.0.4.dist-info/LICENSE
youtube_clipper-1.0.4.dist-info/METADATA
youtube_clipper-1.0.4.dist-info/WHEEL
youtube_clipper-1.0.4.dist-info/entry_points.txt
youtube_clipper-1.0.4.dist-info/RECORD
