Metadata-Version: 2.1
Name: youtube-clipper
Version: 1.0.4
Summary: Tool for finding clips in YouTube videos
Home-page: https://github.com/MCPN/youtube-clipper
License: BSD 3-Clause License
Author: Nick Proskurin
Author-email: n1ckpr0s@yandex.ru
Requires-Python: >=3.10,<4
Classifier: License :: Other/Proprietary License
Classifier: Programming Language :: Python :: 3
Classifier: Programming Language :: Python :: 3.10
Classifier: Programming Language :: Python :: 3.11
Requires-Dist: attrs (>=23.2.0)
Requires-Dist: colorama (>=0.4.6)
Requires-Dist: srt (>=3.5.3)
Requires-Dist: ttconv (>=1.0.8)
Requires-Dist: webvtt-py (>=0.4.6)
Requires-Dist: whoosh (>=2.7.4)
Requires-Dist: yt-dlp (>=2024.07.07)
Project-URL: Repository, https://github.com/MCPN/youtube-clipper
